llama_index/embeddings/baseten/__init__.py
llama_index/embeddings/baseten/base.py
llama_index_embeddings_baseten-0.1.2.dist-info/METADATA
llama_index_embeddings_baseten-0.1.2.dist-info/WHEEL
llama_index_embeddings_baseten-0.1.2.dist-info/licenses/LICENSE
llama_index_embeddings_baseten-0.1.2.dist-info/RECORD
