Metadata-Version: 2.4
Name: llama-index-embeddings-baseten
Version: 0.1.2
Summary: llama-index embeddings baseten integration
Author: alexker
License-Expression: MIT
License-File: LICENSE
Requires-Python: <4.0,>=3.9
Requires-Dist: llama-index-core<0.15,>=0.13.0
Requires-Dist: llama-index-embeddings-openai<0.6,>=0.5.0
